classification_report_as_df/__init__.py
classification_report_as_df/classification_report_as_df.py
classification_report_as_df-0.1.2.dist-info/licenses/LICENSE
classification_report_as_df-0.1.2.dist-info/METADATA
classification_report_as_df-0.1.2.dist-info/WHEEL
classification_report_as_df-0.1.2.dist-info/top_level.txt
classification_report_as_df-0.1.2.dist-info/RECORD
