Metadata-Version: 2.4
Name: classification-report-as-df
Version: 0.1.2
Summary: sklearn-style classification report as a pandas DataFrame
Author-email: Michał Kałuski <kaluski.michal58@gmail.com>
License: MIT License
Project-URL: Repository, https://github.com/Michal58/classification-report-as-df
Classifier: License :: OSI Approved :: MIT License
Classifier: Programming Language :: Python :: 3
Requires-Python: >=3.9
License-File: LICENSE
Requires-Dist: numpy
Requires-Dist: pandas
Requires-Dist: scikit-learn
Requires-Dist: jinja2
Provides-Extra: dev
Requires-Dist: pytest; extra == "dev"
Requires-Dist: beautifulsoup4; extra == "dev"
Dynamic: license-file
